opentelemetry_instrumentation_discordpy/__init__.py
opentelemetry_instrumentation_discordpy/decorators.py
opentelemetry_instrumentation_discordpy/instrumentation.py
opentelemetry_instrumentation_discordpy/metrics.py
opentelemetry_instrumentation_discordpy/version.py
opentelemetry_instrumentation_discordpy/wrappers/__init__.py
opentelemetry_instrumentation_discordpy/wrappers/commands.py
opentelemetry_instrumentation_discordpy/wrappers/event_listeners.py
opentelemetry_instrumentation_discordpy/wrappers/http.py
opentelemetry_instrumentation_discordpy/wrappers/message_operations.py
opentelemetry_instrumentation_discordpy/wrappers/voice.py
opentelemetry_instrumentation_discordpy-0.1.33.dist-info/LICENSE
opentelemetry_instrumentation_discordpy-0.1.33.dist-info/METADATA
opentelemetry_instrumentation_discordpy-0.1.33.dist-info/WHEEL
opentelemetry_instrumentation_discordpy-0.1.33.dist-info/RECORD
