Metadata-Version: 2.1
Name: opentelemetry_instrumentation_discordpy
Version: 0.1.33
Summary: OpenTelemetry instrumentation for discord.py bots
License: BSD-3-Clause
Author: Cookie
Author-email: cookie@idegrity.com
Requires-Python: >=3.9,<4.0
Classifier: License :: OSI Approved :: BSD License
Classifier: Programming Language :: Python :: 3
Classifier: Programming Language :: Python :: 3.9
Classifier: Programming Language :: Python :: 3.10
Classifier: Programming Language :: Python :: 3.11
Classifier: Programming Language :: Python :: 3.12
Requires-Dist: discord-py (>=2.5.0,<3.0.0)
Requires-Dist: opentelemetry-api
Requires-Dist: opentelemetry-instrumentation
Requires-Dist: opentelemetry-sdk
